README.md
setup.cfg
setup.py
gvsnap/__init__.py
gvsnap/cli.py
gvsnap.egg-info/PKG-INFO
gvsnap.egg-info/SOURCES.txt
gvsnap.egg-info/dependency_links.txt
gvsnap.egg-info/entry_points.txt
gvsnap.egg-info/not-zip-safe
gvsnap.egg-info/requires.txt
gvsnap.egg-info/top_level.txt